monitorcontrolskill/Snipsspec
monitorcontrolskill/__init__.py
monitorcontrolskill/monitorcontrolskill.py
snips_skill_monitorcontrol-0.0.2.dist-info/DESCRIPTION.rst
snips_skill_monitorcontrol-0.0.2.dist-info/METADATA
snips_skill_monitorcontrol-0.0.2.dist-info/RECORD
snips_skill_monitorcontrol-0.0.2.dist-info/WHEEL
snips_skill_monitorcontrol-0.0.2.dist-info/metadata.json
snips_skill_monitorcontrol-0.0.2.dist-info/top_level.txt
