Metadata-Version: 2.0
Name: snips-skill-monitorcontrol
Version: 0.0.2
Summary: control power and other features of hdmi monitor
Home-page: UNKNOWN
Author: steve ryan
Author-email: stever@syntithenai.com
License: MIT
Keywords: snips
Platform: UNKNOWN
